{ "type": "FeatureCollection", "crs": { "type": "name", "properties": { "name": "urn:ogc:def:crs:OGC:1.3:CRS84" } }, "features": [ ,
{ "type": "Feature", "properties": { "Name": "William Falk-Wallace", "Description": "Wed Jan 15 17:56:33 EST 2014; Location Accuracy: 65.000000" }, "geometry": { "type": "Point", "coordinates": [ -73.969361, 40.800646, 0.0 ] } },
{ "type": "Feature", "properties": { "Name": "William Falk-Wallace", "Description": "Wed Jan 15 18:58:30 EST 2014; Location Accuracy: 65.000000" }, "geometry": { "type": "Point", "coordinates": [ -73.969622, 40.800612, 0.0 ] } }
]}
