{ "type": "FeatureCollection", "crs": { "type": "name", "properties": { "name": "urn:ogc:def:crs:OGC:1.3:CRS84" } }, "features": [ ,
{ "type": "Feature", "properties": { "Name": "William Falk-Wallace", "Description": "Wed Jan 15 17:56:33 EST 2014; Location Accuracy: 65.000000" }, "geometry": { "type": "Point", "coordinates": [ -73.969361, 40.800646, 0.0 ] } },
{ "type": "Feature", "properties": { "Name": "William Falk-Wallace", "Description": "Wed Jan 15 18:58:30 EST 2014; Location Accuracy: 65.000000" }, "geometry": { "type": "Point", "coordinates": [ -73.969622, 40.800612, 0.0 ] } },
{ "type": "Feature", "properties": { "Name": "William Falk-Wallace", "Description": "Wed Jan 15 18:58:50 EST 2014; Location Accuracy: 65.000000" }, "geometry": { "type": "Point", "coordinates": [ -73.969646, 40.800714, 0.0 ] } },
{ "type": "Feature", "properties": { "Name": "William Falk-Wallace", "Description": "Wed Jan 15 18:59:04 EST 2014; Location Accuracy: 65.000000" }, "geometry": { "type": "Point", "coordinates": [ -73.969717, 40.800823, 0.0 ] } },
{ "type": "Feature", "properties": { "Name": "William Falk-Wallace", "Description": "Wed Jan 15 18:59:39 EST 2014; Location Accuracy: 65.000000" }, "geometry": { "type": "Point", "coordinates": [ -73.969721, 40.800836, 0.0 ] } },
{ "type": "Feature", "properties": { "Name": "William Falk-Wallace", "Description": "Thu Jan 16 01:58:04 EST 2014; Location Accuracy: 65.000000" }, "geometry": { "type": "Point", "coordinates": [ -73.969667, 40.800829, 0.0 ] } },
{ "type": "Feature", "properties": { "Name": "William Falk-Wallace", "Description": "Thu Jan 16 01:58:37 EST 2014; Location Accuracy: 65.000000" }, "geometry": { "type": "Point", "coordinates": [ -73.969690, 40.800824, 0.0 ] } },
{ "type": "Feature", "properties": { "Name": "William Falk-Wallace", "Description": "Fri Jan 17 16:28:57 EST 2014; Location Accuracy: 65.000000" }, "geometry": { "type": "Point", "coordinates": [ -73.969656, 40.800854, 0.0 ] } }
]}
